config_loader/__init__.py
config_loader/loader.py
python_yaml_loader-0.0.3.dist-info/METADATA
python_yaml_loader-0.0.3.dist-info/WHEEL
python_yaml_loader-0.0.3.dist-info/top_level.txt
python_yaml_loader-0.0.3.dist-info/RECORD
