Metadata-Version: 2.4
Name: python-yaml-loader
Version: 0.0.3
Summary: Spring-szerű YAML konfiguráció Python-hoz
Author-email: Zsolt Fehér <feherzsolt999@gmail.com>
Requires-Python: >=3.8
Requires-Dist: pyyaml>=6.0
Provides-Extra: dev
Requires-Dist: pytest; extra == "dev"
Requires-Dist: pytest-cov; extra == "dev"
